fpbase_client/__init__.py
fpbase_client/_local_database.py
fpbase_client/api.py
fpbase_client-0.1.2.dist-info/METADATA
fpbase_client-0.1.2.dist-info/WHEEL
fpbase_client-0.1.2.dist-info/licenses/LICENSE
fpbase_client-0.1.2.dist-info/RECORD
