Metadata-Version: 2.3
Name: fpbase-client
Version: 0.1.2
Summary: A Python client for the FPBase REST API
Project-URL: Homepage, https://github.com/joemans3/fpbase-client
Project-URL: Bug Tracker, https://github.com/joemans3/fpbase-client/issues
Author-email: Baljyot Parmar <baljyotparmar@hotmail.com>
License-File: LICENSE
Classifier: License :: OSI Approved :: MIT License
Classifier: Operating System :: OS Independent
Classifier: Programming Language :: Python :: 3
Requires-Python: >=3.10
Requires-Dist: requests>=2.25.0
Provides-Extra: docs
Requires-Dist: mkdocs-material>=9.0.0; extra == 'docs'
Requires-Dist: mkdocs>=1.5.0; extra == 'docs'
Requires-Dist: mkdocstrings>=0.24.0; extra == 'docs'
Provides-Extra: test
Requires-Dist: pytest-cov>=4.0.0; extra == 'test'
Requires-Dist: pytest>=7.0.0; extra == 'test'
